{"portfolios":[{"accountNum":"123","isIndividual":true,"portfolioValue":3.98,"securities":[{"ticker":"FCASH","quantity":3.0,"price":1438.06},{"ticker":"MSFT","quantity":1.9999998E7,"price":99999.0},{"ticker":"AAPL","quantity":108.84,"price":33.0},{"ticker":"TSLA","quantity":108.84,"price":33.0},{"ticker":"FDRXX","quantity":1.0,"price":1.99}]},{"accountNum":"456","isIndividual":true,"portfolioValue":3.98,"securities":[{"ticker":"FCASH","quantity":2.0,"price":1438.06},{"ticker":"MSFT","quantity":1.9999998E7,"price":99999.0},{"ticker":"AAPL","quantity":111.84,"price":33.0},{"ticker":"TSLA","quantity":138.84,"price":33.0}]}]}